[
  {
    "rank": 1,
    "combination": "sphere+vertical_cylinder+vertical_cylinder",
    "score_mode": "unweighted_log",
    "robust_loss": "huber",
    "robust_f_scale": 0.3,
    "q_min": null,
    "q_max": null,
    "drop_outliers": false,
    "n_removed_outliers": 0,
    "include_mean_candidate": true,
    "exact_nonempty": 3,
    "refine_top_n": 1,
    "refine_max_nfev": 200,
    "refine_target_logrmse": 0.0,
    "refine_stall_patience": 80,
    "refine_stall_tol": 0.0001,
    "refine_attempted": true,
    "refine_success": true,
    "refine_nfev": -1,
    "refine_residual_calls": 339,
    "refine_early_stop_reason": "stalled for 80 residual calls; best_logRMSE=0.248913",
    "refine_best_log_rmse_seen": 0.24891334604540205,
    "refine_message": "stalled for 80 residual calls; best_logRMSE=0.248913",
    "rejected_empty": 0,
    "rejected_exact_nonempty": 0,
    "rejected_forward": 0,
    "rejected_nonfinite": 0,
    "best_source": "sample+refined",
    "unrefined_best_source": "sample",
    "score_weighted_probability": 1.0,
    "posterior_frequency": 1.0,
    "chi2_weighted_probability": 1.0,
    "fit_percent": 0.0,
    "fit_percent_by_log_rmse": 0.0,
    "fit_percent_by_chi2": 0.0,
    "best_score": 0.24891334604540205,
    "best_log_rmse": 0.24891334604540205,
    "best_chi2_weighted": 131.39769128041507,
    "best_robust_log": 0.028219130734287674,
    "best_relative_rmse": 0.8022166848307133,
    "best_linear_rmse": 238.30357612790397,
    "unrefined_best_score": 0.4468691531153486,
    "unrefined_best_log_rmse": 0.4468691531153486,
    "unrefined_best_chi2_weighted": 423.49873983421645,
    "components": [
      {
        "type": "sphere",
        "weight": 0.08493202205619699,
        "params": {
          "R": 8.73379135131836,
          "sigma_R": 4.555596828460693,
          "D": 5.139620304107666,
          "sigma_D": 1.1229418516159058
        }
      },
      {
        "type": "vertical_cylinder",
        "weight": 0.5650438802467111,
        "params": {
          "R": 9.94903564453125,
          "sigma_R": 0.5944122076034546,
          "D": 33.01300811767578,
          "sigma_D": 58.52714157104492
        }
      },
      {
        "type": "vertical_cylinder",
        "weight": 0.35002409769709203,
        "params": {
          "R": 33.22325134277344,
          "sigma_R": 3.5095906257629395,
          "D": 8.272214889526367,
          "sigma_D": 2.896371364593506
        }
      }
    ],
    "global_params": {
      "BG": 1.2989288568496704,
      "sigma_Res": 0.011678988113999367,
      "nu_Res": 5.823711395263672,
      "int_Res": 0.0012963557383045554,
      "k": 184.95480346679688
    },
    "posterior_parameter_stats": {
      "components": [
        {
          "type": "sphere",
          "weight": {
            "median": 0.25320270681580304,
            "p16": 0.25320270681580304,
            "p84": 0.25320270681580304
          },
          "params": {
            "R": {
              "median": 9.204033851623535,
              "p16": 8.97598648071289,
              "p84": 9.38354206085205
            },
            "sigma_R": {
              "median": 3.799100399017334,
              "p16": 3.643570899963379,
              "p84": 3.936826467514038
            },
            "D": {
              "median": 5.343259811401367,
              "p16": 5.205987453460693,
              "p84": 5.487018585205078
            },
            "sigma_D": {
              "median": 0.5502712726593018,
              "p16": 0.5289369821548462,
              "p84": 0.5729603171348572
            }
          }
        },
        {
          "type": "vertical_cylinder",
          "weight": {
            "median": 0.3588781991533024,
            "p16": 0.3588781991533024,
            "p84": 0.3588781991533024
          },
          "params": {
            "R": {
              "median": 17.390098571777344,
              "p16": 17.005868911743164,
              "p84": 17.815099716186523
            },
            "sigma_R": {
              "median": 0.404224157333374,
              "p16": 0.386568546295166,
              "p84": 0.42048758268356323
            },
            "D": {
              "median": 7.922508239746094,
              "p16": 7.712651252746582,
              "p84": 8.147976875305176
            },
            "sigma_D": {
              "median": 0.827308714389801,
              "p16": 0.795431911945343,
              "p84": 0.8638020157814026
            }
          }
        },
        {
          "type": "vertical_cylinder",
          "weight": {
            "median": 0.3879190940308946,
            "p16": 0.3879190940308946,
            "p84": 0.3879190940308946
          },
          "params": {
            "R": {
              "median": 9.627950668334961,
              "p16": 9.396202087402344,
              "p84": 9.865791320800781
            },
            "sigma_R": {
              "median": 0.33228009939193726,
              "p16": 0.3185063302516937,
              "p84": 0.3477920591831207
            },
            "D": {
              "median": 86.79817199707031,
              "p16": 84.50231170654297,
              "p84": 89.14957427978516
            },
            "sigma_D": {
              "median": 20.772525787353516,
              "p16": 19.87807846069336,
              "p84": 21.783174514770508
            }
          }
        }
      ],
      "global_params": {
        "BG": {
          "median": 0.0007588863954879344,
          "p16": 0.0005591048975475132,
          "p84": 0.0009873068192973733
        },
        "sigma_Res": {
          "median": 0.005065680481493473,
          "p16": 0.004999999888241291,
          "p84": 0.005100000184029341
        },
        "nu_Res": {
          "median": 6.117199897766113,
          "p16": 6.117199897766113,
          "p84": 6.117300033569336
        },
        "int_Res": {
          "median": 2.7199976670999604e-07,
          "p16": 2.0328451455497998e-07,
          "p84": 3.5971405054624483e-07
        },
        "k": {
          "median": 212.7718048095703,
          "p16": 194.4324188232422,
          "p84": 230.26852416992188
        }
      }
    }
  }
]